pm4pycvxopt/__init__.py
pm4pycvxopt/util/__init__.py
pm4pycvxopt/util/lp/__init__.py
pm4pycvxopt/util/lp/versions/__init__.py
pm4pycvxopt/util/lp/versions/cvxopt_solver.py
pm4pycvxopt/util/lp/versions/cvxopt_solver_custom_align.py
pm4pycvxopt/util/lp/versions/cvxopt_solver_custom_align_arm.py
pm4pycvxopt/util/lp/versions/cvxopt_solver_custom_align_ilp.py
pm4pycvxopt-0.0.10.dist-info/LICENSE
pm4pycvxopt-0.0.10.dist-info/METADATA
pm4pycvxopt-0.0.10.dist-info/WHEEL
pm4pycvxopt-0.0.10.dist-info/top_level.txt
pm4pycvxopt-0.0.10.dist-info/RECORD
