Metadata-Version: 2.1
Name: pm4pycvxopt
Version: 0.0.10
Summary: Process Mining for Python - CVXOpt Support
Home-page: http://www.pm4py.org
Author: PADS
Author-email: pm4py@pads.rwth-aachen.de
License: GPL 3.0
Project-URL: Documentation, http://pm4py.pads.rwth-aachen.de/documentation/
Project-URL: Source, https://github.com/pm4py/pm4py-source
Project-URL: Tracker, https://github.com/pm4py/pm4py-source/issues
Platform: UNKNOWN
Requires-Dist: pm4py
Requires-Dist: cvxopt
